odoo/addons/account_payment_return_contract_late_fee/CHANGELOG.md
odoo/addons/account_payment_return_contract_late_fee/README.rst
odoo/addons/account_payment_return_contract_late_fee/__init__.py
odoo/addons/account_payment_return_contract_late_fee/__manifest__.py
odoo/addons/account_payment_return_contract_late_fee/i18n/ca_ES.po
odoo/addons/account_payment_return_contract_late_fee/i18n/es.po
odoo/addons/account_payment_return_contract_late_fee/models/__init__.py
odoo/addons/account_payment_return_contract_late_fee/models/contract_contract.py
odoo/addons/account_payment_return_contract_late_fee/models/payment_return.py
odoo/addons/account_payment_return_contract_late_fee/models/res_company.py
odoo/addons/account_payment_return_contract_late_fee/models/res_config_settings.py
odoo/addons/account_payment_return_contract_late_fee/models/res_partner.py
odoo/addons/account_payment_return_contract_late_fee/static/description/icon.png
odoo/addons/account_payment_return_contract_late_fee/tests/__init__.py
odoo/addons/account_payment_return_contract_late_fee/tests/test_payment_return.py
odoo/addons/account_payment_return_contract_late_fee/views/res_config_settings.xml
odoo/addons/account_payment_return_contract_late_fee/views/res_partner_view.xml
odoo12_addon_account_payment_return_contract_late_fee-12.0.1.0.0.dist-info/METADATA
odoo12_addon_account_payment_return_contract_late_fee-12.0.1.0.0.dist-info/WHEEL
odoo12_addon_account_payment_return_contract_late_fee-12.0.1.0.0.dist-info/top_level.txt
odoo12_addon_account_payment_return_contract_late_fee-12.0.1.0.0.dist-info/RECORD
