Metadata-Version: 2.1
Name: odoo12-addon-account-payment-return-contract-late-fee
Version: 12.0.1.0.0
Summary: Payment return late fee for contracts.
Home-page: https://gitlab.com/somitcoop/erp-research/odoo-accounting
Author: Som It Cooperatiu SCCL, Som Connexió SCCL
License: AGPL-3
Platform: UNKNOWN
Classifier: Programming Language :: Python
Classifier: Framework :: Odoo
Classifier: Framework :: Odoo :: 12.0
Classifier: License :: OSI Approved :: GNU Affero General Public License v3
Requires-Python: >=3.5
Requires-Dist: odoo12-addon-account-payment-return
Requires-Dist: odoo12-addon-contract
Requires-Dist: odoo <12.1dev,>=12.0a
